autumn/__init__.py
autumn/client.py
autumn/customers.py
autumn/entities.py
autumn/error.py
autumn/features.py
autumn/http.py
autumn/products.py
autumn/py.typed
autumn/utils.py
autumn/aio/__init__.py
autumn/aio/client.py
autumn/aio/http.py
autumn/aio/stubs.py
autumn/asgi/__init__.py
autumn/asgi/app.py
autumn/asgi/routes/__init__.py
autumn/asgi/routes/core.py
autumn/asgi/routes/customers.py
autumn/asgi/routes/entities.py
autumn/asgi/routes/products.py
autumn/models/balance.py
autumn/models/customer_meta.py
autumn/models/customers.py
autumn/models/entities.py
autumn/models/env.py
autumn/models/features.py
autumn/models/meta.py
autumn/models/products.py
autumn/models/response.py
autumn_py-3.1.9.dist-info/METADATA
autumn_py-3.1.9.dist-info/WHEEL
autumn_py-3.1.9.dist-info/licenses/LICENSE
autumn_py-3.1.9.dist-info/RECORD
