Metadata-Version: 2.4
Name: autumn-py
Version: 3.1.9
Summary: A Python SDK for Autumn's REST API
Project-URL: Source, https://github.com/useautumn/autumn-py
Project-URL: Documentation, https://autumn-py.readthedocs.io
Author-email: John Yeo <johnyeocx@gmail.com>, Viswa Marepalli <reachvishm@gmail.com>
License-Expression: MIT
License-File: LICENSE
Keywords: autumn,payments,stripe
Classifier: Development Status :: 5 - Production/Stable
Classifier: Programming Language :: Python
Classifier: Programming Language :: Python :: 3.9
Classifier: Programming Language :: Python :: 3.10
Classifier: Programming Language :: Python :: 3.11
Classifier: Programming Language :: Python :: 3.12
Classifier: Programming Language :: Python :: 3.13
Classifier: Programming Language :: Python :: Implementation :: CPython
Requires-Python: >=3.9
Requires-Dist: aiohttp>=3.12.15
Requires-Dist: pydantic>=2.11.7
Requires-Dist: requests>=2.32.4
Provides-Extra: aio
Requires-Dist: aiohttp>=3.12.13; extra == 'aio'
Provides-Extra: asgi
Requires-Dist: aiohttp>=3.12.13; extra == 'asgi'
Requires-Dist: starlette>=0.47.1; extra == 'asgi'
Provides-Extra: dev
Requires-Dist: litestar>=2.16.0; extra == 'dev'
Requires-Dist: uvicorn>=0.34.3; extra == 'dev'
Provides-Extra: docs
Requires-Dist: furo>=2024.8.6; extra == 'docs'
Requires-Dist: sphinx-autodoc-typehints>=2.3.0; extra == 'docs'
Requires-Dist: sphinx-tabs>=3.4.7; extra == 'docs'
Requires-Dist: sphinx>=7.4.7; extra == 'docs'
Provides-Extra: tests
Requires-Dist: pytest-asyncio>=1.1.0; extra == 'tests'
Requires-Dist: pytest-cov>=6.2.1; extra == 'tests'
Requires-Dist: pytest>=8.4.1; extra == 'tests'
